{"nodes": [{"id": "c_users_dell_downloads_hexis_src_lib_settings_tsx", "label": "settings.tsx", "file_type": "code", "source_file": "C:\\Users\\DELL\\Downloads\\HEXIS\\src\\lib\\settings.tsx", "source_location": "L1"}, {"id": "lib_settings_settingsmap", "label": "SettingsMap", "file_type": "code", "source_file": "C:\\Users\\DELL\\Downloads\\HEXIS\\src\\lib\\settings.tsx", "source_location": "L6"}, {"id": "lib_settings_settingscontexttype", "label": "SettingsContextType", "file_type": "code", "source_file": "C:\\Users\\DELL\\Downloads\\HEXIS\\src\\lib\\settings.tsx", "source_location": "L8"}, {"id": "lib_settings_settingscontext", "label": "SettingsContext", "file_type": "code", "source_file": "C:\\Users\\DELL\\Downloads\\HEXIS\\src\\lib\\settings.tsx", "source_location": "L15"}, {"id": "lib_settings_usesettings", "label": "useSettings()", "file_type": "code", "source_file": "C:\\Users\\DELL\\Downloads\\HEXIS\\src\\lib\\settings.tsx", "source_location": "L22"}, {"id": "lib_settings_settingsprovider", "label": "SettingsProvider()", "file_type": "code", "source_file": "C:\\Users\\DELL\\Downloads\\HEXIS\\src\\lib\\settings.tsx", "source_location": "L24"}], "edges": [{"source": "c_users_dell_downloads_hexis_src_lib_settings_tsx", "target": "react", "relation": "imports_from", "context": "import", "confidence": "EXTRACTED", "source_file": "C:\\Users\\DELL\\Downloads\\HEXIS\\src\\lib\\settings.tsx", "source_location": "L1", "weight": 1.0}, {"source": "c_users_dell_downloads_hexis_src_lib_settings_tsx", "target": "c_users_dell_downloads_hexis_src_lib_supabase_ts", "relation": "imports_from", "context": "import", "confidence": "EXTRACTED", "source_file": "C:\\Users\\DELL\\Downloads\\HEXIS\\src\\lib\\settings.tsx", "source_location": "L2", "weight": 1.0}, {"source": "c_users_dell_downloads_hexis_src_lib_settings_tsx", "target": "lib_supabase_supabase", "relation": "imports", "context": "import", "confidence": "EXTRACTED", "source_file": "C:\\Users\\DELL\\Downloads\\HEXIS\\src\\lib\\settings.tsx", "source_location": "L2", "weight": 1.0}, {"source": "c_users_dell_downloads_hexis_src_lib_settings_tsx", "target": "c_users_dell_downloads_hexis_src_admin_lib_adminauth_ts", "relation": "imports_from", "context": "import", "confidence": "EXTRACTED", "source_file": "C:\\Users\\DELL\\Downloads\\HEXIS\\src\\lib\\settings.tsx", "source_location": "L3", "weight": 1.0}, {"source": "c_users_dell_downloads_hexis_src_lib_settings_tsx", "target": "lib_adminauth_logadminaction", "relation": "imports", "context": "import", "confidence": "EXTRACTED", "source_file": "C:\\Users\\DELL\\Downloads\\HEXIS\\src\\lib\\settings.tsx", "source_location": "L3", "weight": 1.0}, {"source": "c_users_dell_downloads_hexis_src_lib_settings_tsx", "target": "react_hot_toast", "relation": "imports_from", "context": "import", "confidence": "EXTRACTED", "source_file": "C:\\Users\\DELL\\Downloads\\HEXIS\\src\\lib\\settings.tsx", "source_location": "L4", "weight": 1.0}, {"source": "c_users_dell_downloads_hexis_src_lib_settings_tsx", "target": "lib_settings_settingsmap", "relation": "contains", "confidence": "EXTRACTED", "source_file": "C:\\Users\\DELL\\Downloads\\HEXIS\\src\\lib\\settings.tsx", "source_location": "L6", "weight": 1.0}, {"source": "c_users_dell_downloads_hexis_src_lib_settings_tsx", "target": "lib_settings_settingscontexttype", "relation": "contains", "confidence": "EXTRACTED", "source_file": "C:\\Users\\DELL\\Downloads\\HEXIS\\src\\lib\\settings.tsx", "source_location": "L8", "weight": 1.0}, {"source": "c_users_dell_downloads_hexis_src_lib_settings_tsx", "target": "lib_settings_settingscontext", "relation": "contains", "confidence": "EXTRACTED", "source_file": "C:\\Users\\DELL\\Downloads\\HEXIS\\src\\lib\\settings.tsx", "source_location": "L15", "weight": 1.0}, {"source": "c_users_dell_downloads_hexis_src_lib_settings_tsx", "target": "lib_settings_usesettings", "relation": "contains", "confidence": "EXTRACTED", "source_file": "C:\\Users\\DELL\\Downloads\\HEXIS\\src\\lib\\settings.tsx", "source_location": "L22", "weight": 1.0}, {"source": "c_users_dell_downloads_hexis_src_lib_settings_tsx", "target": "lib_settings_settingsprovider", "relation": "contains", "confidence": "EXTRACTED", "source_file": "C:\\Users\\DELL\\Downloads\\HEXIS\\src\\lib\\settings.tsx", "source_location": "L24", "weight": 1.0}], "raw_calls": [{"caller_nid": "lib_settings_usesettings", "callee": "useContext", "is_member_call": false, "source_file": "C:\\Users\\DELL\\Downloads\\HEXIS\\src\\lib\\settings.tsx", "source_location": "L22"}, {"caller_nid": "lib_settings_settingsprovider", "callee": "useState", "is_member_call": false, "source_file": "C:\\Users\\DELL\\Downloads\\HEXIS\\src\\lib\\settings.tsx", "source_location": "L25"}, {"caller_nid": "lib_settings_settingsprovider", "callee": "useState", "is_member_call": false, "source_file": "C:\\Users\\DELL\\Downloads\\HEXIS\\src\\lib\\settings.tsx", "source_location": "L26"}, {"caller_nid": "lib_settings_settingsprovider", "callee": "useEffect", "is_member_call": false, "source_file": "C:\\Users\\DELL\\Downloads\\HEXIS\\src\\lib\\settings.tsx", "source_location": "L69"}]}